{
  "competitor_analysis": {
    "analysis_date": "2025-08-29",
    "auto_trainer_value_proposition": {
      "core_features": [
        "Takes uploaded documents (technical docs, lectures, notes)",
        "Creates personalized micro-learning paths",
        "Generates practical exercises automatically",
        "Validates task completion"
      ]
    },
    "direct_competitors": {
      "description": "AI-powered platforms that generate learning content from uploaded materials",
      "competitors": [
        {
          "name": "Coursebox AI",
          "founding_year": "Not specified",
          "key_features": [
            "Upload document or video to automatically create courses",
            "AI video course creator with realistic tutorials",
            "Automated assessment and quiz generation",
            "Converts files to eLearning in seconds",
            "Drag-and-drop editing after AI generation"
          ],
          "target_market": "B2B and B2C",
          "pricing": "3 courses for free, paid plans from $10/month",
          "unique_selling_points": [
            "True all-in-one solution combining course authoring and LMS",
            "AI-powered tutoring and assessment features",
            "Video generation capabilities"
          ],
          "geographic_presence": "Global"
        },
        {
          "name": "Mindsmith",
          "founding_year": "Not specified",
          "key_features": [
            "Uses documents as source material for AI content creation",
            "Converts presentations and textbooks into interactive eLearning",
            "Creates engaging scenarios and quizzes",
            "Supports content creation in any language (Google Translate/DeepL)"
          ],
          "target_market": "B2B",
          "pricing": "Free for 2 active shared lessons, Professional plan $39/month",
          "unique_selling_points": [
            "Multi-language course creation capability",
            "Next-gen eLearning authoring with generative AI",
            "Interactive asynchronous eLearning focus"
          ],
          "geographic_presence": "Global"
        },
        {
          "name": "Synthesia",
          "founding_year": "Not specified",
          "key_features": [
            "AI-generated avatar videos for course content",
            "Video-based learning content creation",
            "Eliminates need for camera crew"
          ],
          "target_market": "B2B",
          "pricing": "Contact for pricing",
          "unique_selling_points": [
            "Focus on AI avatar video generation",
            "Professional video content without production costs"
          ],
          "geographic_presence": "Global"
        },
        {
          "name": "Socratic by Google",
          "founding_year": "Acquired by Google",
          "key_features": [
            "Photo-based question solving",
            "Step-by-step explanations from uploaded content",
            "AI-powered homework assistance",
            "Critical thinking guidance"
          ],
          "target_market": "B2C (Students)",
          "pricing": "Free",
          "user_base": "Millions of students globally",
          "unique_selling_points": [
            "Image-based question solving",
            "Google's AI backing",
            "Focus on educational reasoning"
          ],
          "geographic_presence": "Global"
        }
      ]
    },
    "indirect_competitors": {
      "adaptive_learning_platforms": {
        "description": "Platforms that adapt learning paths based on user progress and performance",
        "market_size": "$3.76 billion in 2024, projected to reach $30.79 billion by 2034",
        "competitors": [
          {
            "name": "Knewton",
            "founding_year": "2008",
            "key_features": [
              "Adaptive learning technology integrated into educational platforms",
              "Real-time content adaptation based on student performance",
              "Advanced analytics for personalized learning"
            ],
            "target_market": "B2B (K-12 and Higher Education)",
            "funding": "Acquired by Wiley in May 2019",
            "unique_selling_points": [
              "Pioneer in adaptive learning technology",
              "Integration-focused rather than standalone product",
              "Advanced analytics and personalization"
            ],
            "geographic_presence": "Global"
          },
          {
            "name": "Century Tech",
            "founding_year": "2014",
            "founders": "Priya Lakhani and Rahul Bakrania",
            "key_features": [
              "AI-enabled adaptive learning platform",
              "Teacher content upload and analysis",
              "Personalized learning recommendations",
              "Teacher dashboard with progress analytics"
            ],
            "target_market": "B2B (K-12 and International Schools)",
            "funding": "$12.2M total funding over 6 rounds",
            "valuation": "$19.8M (as of Sep 2019)",
            "user_base": "Used by 100+ British international schools, tens of thousands of schools in 45+ countries",
            "recent_acquisition": "Acquired by Oakdale on March 14, 2025",
            "employees": "109 employees (as of March 2023)",
            "unique_selling_points": [
              "Strong presence in UK and international schools",
              "Used by prestigious institutions (Eton, Dulwich College)",
              "400% usage growth during pandemic"
            ],
            "geographic_presence": "UK, Middle East, Pakistan, 45+ countries"
          }
        ]
      },
      "micro_learning_platforms": {
        "description": "Platforms delivering bite-sized learning content for corporate training",
        "competitors": [
          {
            "name": "Axonify",
            "founding_year": "Not specified",
            "key_features": [
              "Microlearning with daily reinforcement",
              "Gamification for engagement",
              "AI-driven personalized learning paths",
              "Spaced repetition training"
            ],
            "target_market": "B2B (Frontline workforce)",
            "engagement_rate": "83% worker engagement rate",
            "unique_selling_points": [
              "Focus on frontline employee training",
              "High engagement rates",
              "AI-driven reinforcement learning"
            ],
            "geographic_presence": "North America focused"
          },
          {
            "name": "Grovo (now Cornerstone Learn)",
            "founding_year": "2010",
            "founders": "Jeff Fernandez, Nick Narodny, and Surag Mungekar",
            "key_features": [
              "144-second video and audio lessons",
              "Microlearning with quizzes and practice assignments",
              "2500+ lessons on demand"
            ],
            "target_market": "B2B (Corporate training)",
            "funding": "$65 million total (Series A: $5.5M, Series B: $15M, Series C: $40M)",
            "acquisition": "Acquired by Cornerstone OnDemand for $24 million in November 2018",
            "corporate_clients": "PepsiCo, Gap Inc., Magellan Health, NBA",
            "unique_selling_points": [
              "Short-form content focus",
              "Integration with Cornerstone OnDemand",
              "Extensive content library"
            ],
            "geographic_presence": "Global"
          },
          {
            "name": "EdApp (now SC Training)",
            "founding_year": "Not specified",
            "key_features": [
              "Free microlearning platform",
              "Integrated authoring tool",
              "Gamification and spaced repetition",
              "AI-powered course builder"
            ],
            "target_market": "B2B (Construction, healthcare, real estate)",
            "pricing": "Free platform",
            "unique_selling_points": [
              "Completely free platform",
              "Mobile-first design",
              "Multi-award-winning LMS"
            ],
            "geographic_presence": "Global"
          }
        ]
      },
      "ai_coding_assistants": {
        "description": "AI-powered coding platforms with learning and mentorship features",
        "competitors": [
          {
            "name": "GitHub Copilot",
            "founding_year": "2021",
            "key_features": [
              "AI pair programming",
              "Code completion and suggestions",
              "Contextual assistance throughout development lifecycle",
              "Integration with IDEs and GitHub"
            ],
            "target_market": "B2B and B2C (Developers)",
            "pricing": "Individual: $10/month, Business and Enterprise tiers available",
            "productivity_impact": "Up to 55% more productive coding, 75% higher job satisfaction",
            "unique_selling_points": [
              "Market leader in AI coding assistance",
              "Deep integration with development ecosystem",
              "Proven productivity improvements"
            ],
            "geographic_presence": "Global"
          },
          {
            "name": "Replit",
            "founding_year": "Not specified",
            "key_features": [
              "AI-powered Ghostwriter tool",
              "Web-based IDE",
              "Interactive development environment",
              "Code generation and assistance"
            ],
            "target_market": "B2B and B2C (Education and professional development)",
            "funding": "$200+ million total, latest round $97.4M at $1.16B valuation",
            "user_base": "22+ million developers",
            "unique_selling_points": [
              "Web-based, zero-setup approach",
              "Strong in education market",
              "Free tier available"
            ],
            "geographic_presence": "Global"
          },
          {
            "name": "Exercism",
            "founding_year": "Not specified",
            "key_features": [
              "Free coding mentorship platform",
              "Practice exercises in 78 programming languages",
              "Human mentor feedback on code",
              "CLI-first approach"
            ],
            "target_market": "B2C (Individual learners)",
            "funding": "Donation-based, completely free platform",
            "user_base": "19,603 mentors, 14,344 contributors",
            "unique_selling_points": [
              "Completely free forever",
              "Human mentorship focus",
              "78 programming languages supported"
            ],
            "geographic_presence": "Global"
          },
          {
            "name": "Codecademy",
            "founding_year": "2011",
            "key_features": [
              "Interactive coding courses",
              "Hands-on learning environment",
              "Real-time coding challenges",
              "Community interaction and feedback"
            ],
            "target_market": "B2C (Individual learners)",
            "unique_selling_points": [
              "Gamified learning approach",
              "Large course library",
              "Strong community features"
            ],
            "geographic_presence": "Global"
          }
        ]
      },
      "corporate_training_ai_platforms": {
        "description": "Enterprise learning management systems with AI-powered features",
        "competitors": [
          {
            "name": "Docebo",
            "founding_year": "2005",
            "key_features": [
              "AI-first LMS with Skills feature",
              "Automated content analysis and tagging",
              "AI Virtual Coaching with scenario-based simulations",
              "Deep Search functionality"
            ],
            "target_market": "B2B (Mid-market and Enterprise)",
            "funding": "Public company (TSX: DCBO, NASDAQ: DCBO)",
            "early_funding": "€2.4M (2012), $3M (2015)",
            "ai_strategy": "AI-first roadmap strategy declared in 2025",
            "acquisitions": "Acquired Edugo.AI in 2023",
            "geographic_presence": "Global (Toronto, Athens GA, London, Paris, Berlin, Biassono, Melbourne, Dubai)",
            "unique_selling_points": [
              "AI-first strategy",
              "FedRAMP Moderate Authorization",
              "Enterprise-focused features"
            ]
          },
          {
            "name": "TalentLMS",
            "founding_year": "Not specified",
            "key_features": [
              "AI course creator for rapid course development",
              "Modernized user interface",
              "AI skills-based training",
              "Test generation and course translation (in development)"
            ],
            "target_market": "B2B (Small to mid-market)",
            "pricing": "Freemium model, Grow plan $359/month (70 users)",
            "unique_selling_points": [
              "User-friendly interface",
              "Strong mobile offering",
              "AI course creation focus"
            ],
            "geographic_presence": "Global"
          }
        ]
      },
      "document_to_course_platforms": {
        "description": "Specialized platforms for converting documents into structured learning content",
        "competitors": [
          {
            "name": "Coassemble",
            "founding_year": "Not specified",
            "key_features": [
              "AI conversion of PDF, DOCX, PPTX to microlearning",
              "AI-generated quizzes from course content",
              "Learner feedback collection"
            ],
            "target_market": "B2B",
            "pricing": "Freemium, paid plans from $10/month",
            "unique_selling_points": [
              "Focus on microlearning conversion",
              "Multiple document format support"
            ]
          },
          {
            "name": "Arlo",
            "founding_year": "Not specified",
            "key_features": [
              "Upload PDFs and documents for course conversion",
              "Drag-and-drop course builder",
              "Automated admin workflows"
            ],
            "target_market": "B2B (Training providers)",
            "unique_selling_points": [
              "User-friendly for non-technical users",
              "Comprehensive training management"
            ]
          },
          {
            "name": "Mini Course Generator",
            "founding_year": "Not specified",
            "key_features": [
              "Interactive mini-course creation",
              "AI voiceovers in 120+ languages",
              "Microlearning material generation"
            ],
            "target_market": "B2B (SMEs)",
            "pricing": "Free tools, paid plans from $18/month",
            "unique_selling_points": [
              "Multi-language voiceover capability",
              "Focus on bite-sized content"
            ]
          },
          {
            "name": "Easygenerator",
            "founding_year": "Not specified",
            "key_features": [
              "EasyAI for course development acceleration",
              "Automated translation via machine learning",
              "Subject matter expert-focused design"
            ],
            "target_market": "B2B (Enterprise)",
            "user_base": "50,000+ users worldwide",
            "pricing": "Paid plans from $108/month",
            "unique_selling_points": [
              "Large user base",
              "Focus on SME empowerment",
              "Advanced AI assistant"
            ]
          }
        ]
      }
    },
    "market_insights": {
      "adaptive_learning_market": {
        "size_2024": "$3.76 billion",
        "projected_2034": "$30.79 billion",
        "cagr": "22.01%",
        "regional_leaders": {
          "north_america": "35% market share",
          "europe": "28% projected by forecast end"
        }
      },
      "ai_personalized_learning_market": {
        "size_2024": "$6.5 billion",
        "projected_2034": "$208.2 billion",
        "cagr": "41.4%"
      },
      "key_trends": [
        "AI-first learning platform strategies",
        "Increased focus on personalized learning paths",
        "Integration of generative AI for content creation",
        "Mobile-first learning approaches",
        "Microlearning and spaced repetition gaining traction",
        "Document-to-course automation becoming standard",
        "Enterprise adoption of AI-powered training solutions"
      ]
    },
    "competitive_positioning_opportunities": {
      "direct_competitor_gaps": [
        "Most platforms focus on either content creation OR delivery, not both seamlessly",
        "Limited focus on practical exercise generation and validation",
        "Weak task completion verification systems",
        "Generic personalization rather than deep document analysis"
      ],
      "market_positioning": [
        "Auto-trainer's unique combination of document analysis + exercise generation + completion validation is underserved",
        "Technical document processing for professional development is a niche with high value",
        "Micro-learning paths with practical validation could differentiate from content-creation-only platforms"
      ],
      "key_differentiators": [
        "Deep technical document comprehension",
        "Automated practical exercise generation (not just quizzes)",
        "Task completion validation system",
        "Personalized micro-learning paths based on document analysis"
      ]
    }
  }
}